typer/__init__.py
typer/__main__.py
typer/_completion_classes.py
typer/_completion_shared.py
typer/_types.py
typer/_typing.py
typer/cli.py
typer/colors.py
typer/completion.py
typer/core.py
typer/extra_click_types.py
typer/main.py
typer/models.py
typer/params.py
typer/py.typed
typer/rich_utils.py
typer/testing.py
typer/utils.py
typer_doc-0.16.0.3.dist-info/METADATA
typer_doc-0.16.0.3.dist-info/WHEEL
typer_doc-0.16.0.3.dist-info/entry_points.txt
typer_doc-0.16.0.3.dist-info/licenses/LICENSE
typer_doc-0.16.0.3.dist-info/RECORD
