Metadata-Version: 2.1
Name: typer-doc
Version: 0.16.0.3
Summary: Typer, build great CLIs. Easy to code. Based on Python type hints and docstrings.
Author-Email: =?utf-8?q?Sebasti=C3=A1n_Ram=C3=ADrez?= <tiangolo@gmail.com>
Classifier: Intended Audience :: Information Technology
Classifier: Intended Audience :: System Administrators
Classifier: Operating System :: OS Independent
Classifier: Programming Language :: Python :: 3
Classifier: Programming Language :: Python
Classifier: Topic :: Software Development :: Libraries :: Application Frameworks
Classifier: Topic :: Software Development :: Libraries :: Python Modules
Classifier: Topic :: Software Development :: Libraries
Classifier: Topic :: Software Development
Classifier: Typing :: Typed
Classifier: Development Status :: 4 - Beta
Classifier: Intended Audience :: Developers
Classifier: Programming Language :: Python :: 3 :: Only
Classifier: Programming Language :: Python :: 3.7
Classifier: Programming Language :: Python :: 3.8
Classifier: Programming Language :: Python :: 3.9
Classifier: Programming Language :: Python :: 3.10
Classifier: Programming Language :: Python :: 3.11
Classifier: Programming Language :: Python :: 3.12
Classifier: Programming Language :: Python :: 3.13
Classifier: License :: OSI Approved :: MIT License
Project-URL: Homepage, https://github.com/buhanec/typer-doc
Project-URL: Documentation, https://typer.tiangolo.com
Project-URL: Repository, https://github.com/buhanec/typer-doc
Project-URL: Issues, https://github.com/buhanec/typer-doc/issues
Project-URL: Changelog, https://typer.tiangolo.com/release-notes/
Requires-Python: >=3.7
Requires-Dist: click>=8.0.0
Requires-Dist: typing-extensions>=3.7.4.3
Requires-Dist: shellingham>=1.3.0
Requires-Dist: rich>=10.11.0
Requires-Dist: docstring-parser>=0.16
Requires-Dist: backports.zoneinfo; python_version < "3.9"
Requires-Dist: pytz
